magent_ui_langchain/__init__.py
magent_ui_langchain/app.py
magent_ui_langchain/config.py
magent_ui_langchain/core/__init__.py
magent_ui_langchain/core/adaptor_registry.py
magent_ui_langchain/core/base_adaptor.py
magent_ui_langchain/core/current_executor.py
magent_ui_langchain/core/event.py
magent_ui_langchain/core/langchain_adaptor.py
magent_ui_langchain/core/langchain_openai_executor.py
magent_ui_langchain/core/langchain_tongyi_executor.py
magent_ui_langchain/core/utils.py
magent_ui_langchain/routers/__init__.py
magent_ui_langchain/routers/main.py
magent_ui_langchain/routers/chat/__init__.py
magent_ui_langchain/routers/chat/router.py
magent_ui_langchain/static/255.async.js
magent_ui_langchain/static/567.async.js
magent_ui_langchain/static/989.chunk.css
magent_ui_langchain/static/favicon.ico
magent_ui_langchain/static/index.html
magent_ui_langchain/static/preload_helper.js
magent_ui_langchain/static/umi.css
magent_ui_langchain/static/umi.js
magent_ui_langchain/static/static/devopicons.3c46801a.woff2
magent_ui_langchain/static/static/file-icons.2cbb51ef.woff2
magent_ui_langchain/static/static/fontawesome-webfont.2b13baa7.eot
magent_ui_langchain/static/static/fontawesome-webfont.8a7cb27d.ttf
magent_ui_langchain/static/static/fontawesome-webfont.cf011583.woff
magent_ui_langchain/static/static/fontawesome-webfont.e9955780.woff2
magent_ui_langchain/static/static/fontawesome-webfont.f05dad85.svg
magent_ui_langchain/static/static/fontawesome.e9955780.woff2
magent_ui_langchain/static/static/mfixx.8e0807ce.woff2
magent_ui_langchain/static/static/octicons.c982f59d.woff2
magent_ui_langchain/templates/index.html
magent_ui_langchain-0.1.0.dev0.dist-info/METADATA
magent_ui_langchain-0.1.0.dev0.dist-info/WHEEL
magent_ui_langchain-0.1.0.dev0.dist-info/RECORD
